{
    "version": "7",
    "dialect": "postgresql",
    "entries": [
        {
            "idx": 0,
            "version": "7",
            "when": 1781269848014,
            "tag": "0000_magical_kitty_pryde",
            "breakpoints": true
        },
        {
            "idx": 1,
            "version": "7",
            "when": 1781435632809,
            "tag": "0001_curvy_wiccan",
            "breakpoints": true
        },
        {
            "idx": 2,
            "version": "7",
            "when": 1781506339893,
            "tag": "0002_broad_unicorn",
            "breakpoints": true
        }
    ]
}
